dwscripter/__init__.py
dwscripter/__main__.py
dwscripter/bridge.py
dwscripter/rulesets.py
dwscripter/scripter.py
dwscripter/sample/sample.csv
dwscripter-0.0.1.dist-info/LICENSE
dwscripter-0.0.1.dist-info/METADATA
dwscripter-0.0.1.dist-info/WHEEL
dwscripter-0.0.1.dist-info/dependency_links.txt
dwscripter-0.0.1.dist-info/entry_points.txt
dwscripter-0.0.1.dist-info/top_level.txt
dwscripter-0.0.1.dist-info/RECORD
