Metadata-Version: 2.1
Name: dwscripter
Version: 0.0.1
Summary: DW Script Generator
Author: Soumyajit Sinha
License: MIT
Classifier: License :: OSI Approved :: MIT License
Classifier: Programming Language :: Python :: 3
Classifier: Development Status :: 3 - Alpha
Classifier: Intended Audience :: Developers
License-File: LICENSE
Requires-Dist: pandas
Requires-Dist: tabulate
Requires-Dist: numpy
Requires-Dist: click
Requires-Dist: twine
